audoma/__init__.py
audoma/choices.py
audoma/decorators.py
audoma/example_generators.py
audoma/examples.py
audoma/hooks.py
audoma/links.py
audoma/mixins.py
audoma/openapi.py
audoma/operations.py
audoma/plumbing.py
audoma/schema.py
audoma/settings.py
audoma/django/__init__.py
audoma/django/db/__init__.py
audoma/django/db/fields.py
audoma/django/db/models.py
audoma/django/forms/__init__.py
audoma/django/forms/fields.py
audoma/drf/__init__.py
audoma/drf/decorators.py
audoma/drf/fields.py
audoma/drf/filters.py
audoma/drf/generics.py
audoma/drf/mixins.py
audoma/drf/routers.py
audoma/drf/serializers.py
audoma/drf/validators.py
audoma/drf/viewsets.py
audoma/tests/__init__.py
audoma/tests/test_audoma_django_db_fields.py
audoma/tests/test_decorators.py
audoma/tests/test_generics.py
audoma/tests/test_openapi.py
audoma/tests/test_plumbing.py
audoma/tests/test_schema.py
audoma/tests/testtools.py
audoma/tests/drf/__init__.py
audoma/tests/drf/test_fields.py
audoma/tests/drf/test_mixins.py
audoma/tests/drf/test_serializers.py
audoma/tests/drf/test_validators.py
audoma-0.6.8.dist-info/LICENSE
audoma-0.6.8.dist-info/METADATA
audoma-0.6.8.dist-info/WHEEL
audoma-0.6.8.dist-info/top_level.txt
audoma-0.6.8.dist-info/RECORD
