Metadata-Version: 2.1
Name: audoma
Version: 0.6.8
Summary: API Automatic Documentation Maker - DRF-SPECTACULAR wrapper
Home-page: UNKNOWN
Author: ITEO
License: UNKNOWN
Platform: UNKNOWN
Classifier: Intended Audience :: Developers
Classifier: Operating System :: OS Independent
Classifier: Environment :: Web Environment
Classifier: Topic :: Documentation
Classifier: Topic :: Software Development :: Code Generators
Classifier: Programming Language :: Python
Classifier: Programming Language :: Python :: 3
Classifier: Programming Language :: Python :: 3.7
Classifier: Programming Language :: Python :: 3.8
Classifier: Programming Language :: Python :: 3.9
Classifier: Framework :: Django
Classifier: Framework :: Django :: 2.2
Classifier: Framework :: Django :: 3.0
Classifier: Framework :: Django :: 3.1
Classifier: Framework :: Django :: 3.2
Classifier: Framework :: Django :: 4.0
Requires-Dist: Django <=4.0.0,>=2.2.15
Requires-Dist: djangorestframework <=3.13.999,>=3.10
Requires-Dist: exrex <=0.11.0,>=0.5.0
Requires-Dist: django-phonenumber-field <=6.1.0,>=5.0.0
Requires-Dist: django-macaddress <=1.8.0,>=1.6.0
Requires-Dist: phonenumbers <=8.13.10
Requires-Dist: django-extensions <=3.2.1
Requires-Dist: django-filter <=22.2
Requires-Dist: drf-spectacular <=0.21.2
Requires-Dist: django-money <=2.1
Requires-Dist: lorem <=0.1.1
Requires-Dist: drf-extra-fields ==v3.4.1
